vgis_aiutils/__init__.py
vgis_aiutils/aiTools.py
vgis_aiutils/gpuTools.py
vgis_nlp/__init__.py
vgis_nlp/pasreTextTool.py
vgis_nlp/pingyin.py
vgis_ocr/__init__.py
vgis_ocr/ocrTools.py
vgis_pose/__init__.py
vgis_pose/aiSettings.py
vgis_pose/peopleDetect.py
vgis_pose/peopleDodySep.py
vgis_sample/__init__.py
vgis_sample/sampleImageSegmetaion.py
vgis_sample/sampleLabelsOperator.py
vgis_sklearn/__init__.py
vgis_sklearn/acfPolyfit.py
vgis_sklearn/sklearnTool.py
vgis_ai-1.3.7.dist-info/METADATA
vgis_ai-1.3.7.dist-info/WHEEL
vgis_ai-1.3.7.dist-info/top_level.txt
vgis_ai-1.3.7.dist-info/RECORD
