Metadata-Version: 2.1
Name: vgis_ai
Version: 1.3.7
Summary: A libary for ai operator
Home-page: https://github.com/gisfanmachel/vgisAi
Author: gisfanmachel
Author-email: gisfanmachel@gmail.com
Keywords: utils,setuptools,development
Classifier: Development Status :: 3 - Alpha
Classifier: Intended Audience :: Developers
Classifier: Topic :: Software Development :: Build Tools
Classifier: License :: OSI Approved :: MIT License
Classifier: Programming Language :: Python :: 3
Classifier: Programming Language :: Python :: 3.7
Classifier: Programming Language :: Python :: 3.8
Classifier: Programming Language :: Python :: 3.9
Classifier: Programming Language :: Python :: 3.10
Classifier: Programming Language :: Python :: 3 :: Only
Requires-Python: >=3.7, <4
Requires-Dist: opencv-python
Requires-Dist: Pillow
Requires-Dist: numpy
Requires-Dist: pandas
Requires-Dist: loguru
Requires-Dist: scikit-learn
Requires-Dist: scipy
Requires-Dist: torch
Requires-Dist: baidu-aip
Requires-Dist: imgaug
Requires-Dist: shapely
Requires-Dist: pycocotools
Requires-Dist: cityscapesscripts
Requires-Dist: requests
Requires-Dist: vgis_utils
Requires-Dist: vgis_log
Requires-Dist: vgis_gis
